{
  "Create Your Account": "أنشئ حسابك",
  "Register now and manage your travel bookings, payments, and groups all in one place": "سجّل الآن وأدِر حجوزاتك للسفر والمدفوعات والمجموعات جميعها في مكان واحد",

  "Full Name": "الاسم الكامل",
  "Contact No (Saudi)": "رقم الجوال (السعودي)",
  "Iqama Number": "رقم الإقامة",
  "Iqama Expiry Date": "تاريخ انتهاء الإقامة",

  "Nationality": "الجنسية",
  "Select nationality": "اختر الجنسية",

  "City": "المدينة",
  "Select city": "اختر المدينة",
  "Book verified vehicles between Makkah, Madinah, and Jeddah with trusted service providers":"احجز مركبات موثوقة بين مكة والمدينة وجدة مع مزودي خدمة موثوقين",

  "Residential Address": "العنوان السكني",

  "Passport Number": "رقم جواز السفر",
  "Passport Expiry Date": "تاريخ انتهاء جواز السفر",
  "Don’t have an account":"ما عندك حساب؟",
  "Email": "البريد الإلكتروني",
  "Password": "كلمة المرور",
  "Confirm password": "تأكيد كلمة المرور",
  "Register now and manage your travel bookings, payments, and groups all in one place.": "سجّل الآن وأدِر حجوزاتك للسفر والمدفوعات والمجموعات جميعها في مكان واحد",

  "Already have an account?": "هل لديك حساب؟",
  "Register":"التسجيل",
  "Back to home":"الرجوع إلى الرئيسية",
  "Let's Build Something Exceptional Together. Take the first step toward your digital transformation with a free consultation from experts.": "لنصنع شيئًا استثنائيًا معًا. ابدأ خطوتك الأولى نحو التحول الرقمي مع استشارة مجانية من الخبراء",
 "Recommended Packages": "الباقات الموصى بها",
  "Welcome Back!": "مرحبًا بعودتك",
  "Login to manage your travel bookings, payments, and groups all in one place.": "سجّل الدخول لإدارة حجوزات سفرك، ومدفوعاتك، ومجموعاتك كل ذلك في مكان واحد",
"Get up to 25% off on selected tour packages this month": "احصل على خصم يصل إلى 25٪ على باقات الرحلات المختارة هذا الشهر",
  "Login": "تسجيل الدخول",
  "Don't have an account?": "ليس لديك حساب؟",
   "Selected": "تم الاختيار",
  "Continue": "متابعة",
 

  "Trip Details": "تفاصيل الرحلة",

  "Confirm": "تأكيد",
  "Choose Your Vehicle": "اختر مركبتك",
  "Select a comfortable vehicle for your journey": "اختر مركبة مريحة لرحلتك",
 "Return Date": "تاريخ العودة",
  "Plan Your Journey": "خطّط رحلتك",
  "Select your route and preferred travel time": "اختر مسارك ووقت السفر المفضل",
 "Departure Date": "تاريخ المغادرة",
"Return Time": "وقت العودة",
  "Trip Type": "نوع الرحلة",
  "One Way": "ذهاب فقط",
  "Driver Assignment": "تعيين السائق",
  "Round Trip": "ذهاب وعودة",
"Confirm Booking": "تأكيد الحجز",
  "Travel Date": "تاريخ السفر",

  "Departure": "مغادرة",
  "Departure City": "مدینۃ المغادرۃ",


  "Destination": "الوصول",
  "Destination City": "مدينة الوصول",


  "Start Time": "وقت الانطلاق",
  "Hour": "ساعة",
  "Min": "دقيقة",
  "AM/PM": "ص / م",

  "Continue to Vehicle Selection": "تابع لاختيار المركبة",
 "Profile": "الملف الشخصي",
 "Way To Haramain Logo": "شعار طريق الحرمين",
  "How It Works": "کیف یعمل",
  "Vehicle Categories": "فئات السیارات",
  "Why Choose Us": "لماذا تختارنا",
  "Copyright": "حقوق الطبع والنشر",
  "Way To Haramain": "طريق الحرمين",
  "support_email": "support@waytoharamain.com",
  "Support": "الدعم",

  "We're here to help with any questions or issues": "نحن هنا لمساعدتك في أي أسئلة أو مشكلات",

  "WhatsApp Support": "دعم واتساب",
  "Chat with us instantly": "تواصل معنا فورًا عبر الدردشة",


  "Call Support": "اتصل بالدعم",
  "Speak directly with our team": "تحدث مباشرة مع فريقنا",

  "FAQ": "الأسئلة الشائعة",
  "Find answers to common questions": "احصل على إجابات للأسئلة الشائعة",
  "Browse FAQs": "تصفح الأسئلة",

  "Report an Issue": "الإبلاغ عن مشكلة",
  "Issue Type": "نوع المشكلة",
  "Select issue type": "اختر نوع المشكلة",

  "Describe Your Issue": "وضح المشكلة",
  "Please provide as much detail as possible": "من فضلك أضف كل التفاصيل الممكنة",

  "Submit Issue": "إرسال المشكلة",
  "Frequently Asked Questions": "الأسئلة الشائعة",
  "Service Providers": "مقدمي الخدمة",
  "Trusted Partners": "الشركاء الموثوقون",
  "Top Rated Providers" : "أفضل المزودين تقييمًا",
  

  "Choose from our verified transport partners for your spiritual journey": "اختر من شركائنا الموثوقين لرحلتك الروحية",

  "Verified Partners": "الشركاء الموثوقون",
  "Average Rating": "تقييم متوسط",
  "Happy Customers": "عملاء سعداء",

  "Browse All Providers": "تصفح جميع المزودين",
  "Search and filter to find the perfect partner for your journey": "بحث واستخدم الفلتر لتجد الشريك المثالي لرحلتك",

  "Search vendors by name": "ابحث عن المزودين بالاسم",
  "Filters" : "الفلاتر",
  "Showing" : "عرض",


  "Can't find the right provider?": "ما حصلت مزود الخدمة المناسب؟",
  "Our support team is here to help you find the perfect transport partner for your journey": "فريق الدعم لدينا موجود لمساعدتك في العثور على شريك النقل المناسب لرحلتك",

  "Contact Support": "الاتصال بالدعم",

  "Profile & Settings": "الملف الشخصي والإعدادات",
  "Manage your account and preferences": "إدارة حسابك وتفضيلاتك",

  "Profile Information": "معلومات الملف الشخصي",
  "Verified User": "مستخدم موثّق",

  "Phone Number": "رقم الجوال",
  "Email Address": "عنوان البريد الإلكتروني",
  "Preferred Language": "اللغة المفضلة",

  "Edit Profile": "تعديل الملف الشخصي",

  "Settings": "الإعدادات",
  "Push Notifications": "الإشعارات الفورية",
  "Receive updates about your bookings": "تلقي إشعارات فورية حول حجوزاتك",

  "WhatsApp Updates": "تحديثات واتساب",
  "Get booking confirmations via WhatsApp": "تلقي تأكيدات الحجز عبر واتساب",


  "My Rides": "رحلاتي",
  "View and manage your ride bookings": "إدارة حجوزات رحلاتك",

 

  "Vehicle": "مركبة",
  "Driver": "سائق",

  "Cancel Ride": "إلغاء الرحلة",
  "Cancel This Ride?": "إلغاء هذه الرحلة؟",
  "Reason for Cancellation": "سبب الإلغاء",
  "Select a reason": "اختر سببًا",
  "Keep Ride": "ابقِ الرحلة",
  "Confirm Cancellation": "تأكيد الإلغاء",
  "Back to Dashboard": "الرجوع إلى لوحة التحكم",

  "My Packages": "باقاتي",
  "View and manage your packages bookings": "استعرض وأدر حجوزات باقاتك",

  "Upcoming": "القادمة",
  "Completed": "مكتمل",
  "Duration": "المدة",
  "Capacity": "السعة",
  "Umrah": "عمرة",

  "Pending": "معلق",
  "Starting from": "ابتداءً من",
  "Cancel": "إلغاء",
  "View Details": "عرض التفاصيل",
  "~Seamless~": "سلس",
  "Hajj & Umrah": "الحج والعمرة",
  "Transportation Booking": "حجز النقل",
   "Book verified vehicles between Makkah, Madinah, and": "احجز مركبات موثوقة بين مكة والمدينة و",
  "Jeddah": "جدة",
  "Trusted by": "موثوق من قبل",
  "500+ clients": "أكثر من 500 عميل",
  "all over the world": "حول العالم",
   "~ Travel with Ease ~": "~ سافر بسهولة ~",
  "with trusted service providers": "مع مزودي خدمة موثوقين",

  "Hajj & Umrah Transportation Booking": "حج وعمرہ – حجز النقل",
  "Book verified vehicles between Makkah, Madinah, and Jeddah with trusted service providers": "احجز سيارات موثوقة بين مكة، المدينة وجدة مع مزوّدي خدمة معتمدين",
  "Trusted by 500+ clients all over the world": "موثوق من قبل أكثر من 500 عميل حول العالم",

  "Booking": "الحجز",
  "Register as Vendor": "التسجيل كبائع",
   "~ Choose The Right ~": "~ اختر الأنسب ~",
  "Vehicle For Your Journey": "السیارۃ لرحلتك",
  "From luxury sedans to spacious coasters, select the ride that best suits your comfort and group size.": "من السيارات الفاخرة إلى الحافلات الواسعة، اختر الرحلة التي تناسب راحتك وحجم مجموعتك.",
  "Coaster": "كوستر",
  "GMC": "جي إم سي",
  "Lexus": "لكزس",
  "Staria": "ستاريا",
  "~ Why Haramain ~": "~ لماذا الحرمين ~",
  "Trust Way To Haramain": "طريقة موثوقة إلى الحرمين",
  "At Way To Haramain, every journey is treated with the respect and care it deserves. We combine technology, verified service providers, and human support to ensure pilgrims experience peace of mind from the moment they book to the moment they arrive.": "في Way To Haramain، نحرص على أن تُعامل كل رحلة بالاحترام والرعاية التي تستحقها. نجمع بين التقنية، ومزودي الخدمة الموثوقين، والدعم البشري لضمان راحة الحجاج من لحظة الحجز حتى وصولهم.",
  "Pilgrims in front of hotel": "الحجاج أمام الفندق",
  "From carefully vetted drivers to secure online booking and 24/7 support, every detail is designed to make your sacred travel stress-free and seamless.":"من السائقين المختارين بعناية إلى الحجز الإلكتروني الآمن والدعم المتواصل على مدار الساعة، كل التفاصيل مصممة لجعل رحلتك المقدسة خالية من التوتر وسلسة تمامًا",
  "~ For Travel ~": "~ للسفر ~",
  "Agents Group": "مجموعة الوكلاء",
  "Organizers": "المنظمون",
  "Whether you handle small groups or large delegations, our platform simplifies coordination, payments, and communication — all in one place.": "سواء كنت تتعامل مع مجموعات صغيرة أو وفود كبيرة، فإن منصتنا تُبسّط التنسيق والمدفوعات والتواصل — كل ذلك في مكان واحد.",
  "Join an Agent": "انضم إلى وكيل",
  "Background Banner": "لافتة خلفية",
  "Agent": "وكيل",
   "~ What Our ~": "~ آراء الحجاج ~",
  "Travelers Say": "ماذا يقول المسافرون",
  "Trusted by pilgrims for safe, comfortable, and reliable travel between Makkah, Madinah, and Jeddah, with verified vehicles and instant WhatsApp confirmations.": "موثوق من الحجاج للسفر الآمن والمريح بين مكة والمدينة وجدة، مع مركبات موثوقة وتأكيدات فورية عبر الواتساب.",
  "Ahmed R., Jeddah": "أحمد ر., جدة",
  "Umrah Traveler": "مسافر عمرة",
  "Kaaba": "الكعبة",
  "Find your ideal route between Makkah, Madinah, and Jeddah in a few clicks.": "اختر مسارك المثالي بين مكة والمدينة وجدة بسهولة",
 
  "Choose the vehicle that suits your comfort and group size.": "اختر السيارة المناسبة لراحتك وعدد أفراد مجموعتك",

  "Enjoy reliable travel with trusted drivers and instant WhatsApp updates.": "استمتع بالسفر الموثوق مع سائقين موثوقين وتحديثات فورية عبر واتساب.",

  "Instant ride confirmation with secure Mada, Visa, and Apple Pay payments.": "تأكيد الرحلة فورًا مع الدفع الآمن عبر مدى، التاشیرۃ، وApple Pay",

  "Travel with Ease": "سافر بسهولة",
  "Makkah & Madinah in 4 Simple Steps": "مكة والمدينة في أربع خطوات بسيطة",
  "From searching your Car comfortably, we make your sacred journey seamless and stress-free.": "من البحث عن سيارتك براحة، نجعل رحلتك المقدسة سلسة وخالية من التوتر",

  "Search Your Route": "ابحث عن مسارك",
  "Find your ideal route between Makkah": "اعثر على مسارك المثالي بين مكة",
"Review Your Booking": "مراجعة حجزك",
  "Please verify all details before confirming": "يرجى التحقق من جميع التفاصيل قبل التأكيد",
  "Select Vehicle": "اختر السیارۃ",
  "Book This Package": "احجز هذه الباقة",
  "per person": "لكل شخص",
   "Group Size": "حجم المجموعة",
    "Support Center": "مركز الدعم",
  "Language": "اللغة",
  "Choose the vehicle that suits your comfort and group size": "اختر المركبة التي تناسب راحتك وعدد أفراد مجموعتك.",
"Need help? Contact our support team for assistance.": "هل تحتاج مساعدة؟ تواصل مع فريق الدعم الخاص بنا للمساعدة.",
  "Travel Comfortably": "سافر براحة",
  "Enjoy reliable travel with trusted drivers and instant": "استمتع برحلة موثوقة مع سائقين معتمدين وتحديثات فورية عبر واتساب",
"Our most trusted and highly rated partners" : "شركاؤنا الأكثر ثقة والأعلى تقييمً",
  "Book & Pay": "احجز وادفع",
  "Instant ride confirmation with secure Mada, Visa,": "تأكيد الرحلة الفوري مع مدع، فيزا،","way to Harmain": "الطريق إلى الحرمين",
  "Welcome back": "أهلاً بعودتك",
  "Premium Member": "عضو مميز",
  "Dashboard": "لوحة التحكم",

  "Flash Sale Today": "تخفيض اليوم",
  "Makkah-Madinah Express": "إكسبريس مكة–المدينة",
  "Premium transport between the holy cities": "نقل مميز بين المدينتين المقدستين",
  "Group Savings": "الادخار الجماعي",
  "Family Package Bonanza": "عرض العائلة المميز",
  "Save more when you travel together": "وفر أكثر عند السفر معًا",
  "Limited Time Offer": "عرض لفترة محدودة",
  "Umrah Season Special": "عرض خاص لموسم العمرة",
  "Book your spiritual journey with exclusive rates": "احجز رحلتك الروحية بأسعار حصرية",

  "Logout": "تسجيل الخروج",
  "Quick Actions": "إجراءات سريعة",
  "Book a Ride": "احجز رحلة",
  "Schedule your next journey": "جدول رحلتك القادمة",
  "View My Rides": "عرض رحلاتي",
  "Track all your bookings": "تتبع جميع حجوزاتك",
  "Services Provider": "موفر الخدمات",
  "Explore tour packages": "استكشف باقات الرحلات",
  "Quick Booking": "حجز سريع",

  "From": "من",
  "Select departure city": "اختر مدینۃ المغادرۃ",
  "To": "إلى",
  "Select destination city": "اختر مدينة الوصول",
  "Date": "التاريخ",
  "Continue Booking": "تابع الحجز",

  "Need Help?": "تحتاج مساعدة؟",
  "Chat with us on WhatsApp for instant support": "تحدث معنا على واتساب للدعم الفوري",
  "Open WhatsApp": "افتح واتساب",

  "Special Offer": "عرض خاص",
  "Winter Package Sale": "عرض باقة الشتاء",
  "View Offers": "شاهد العروض",
  "View All": "عرض الکل"
}
